{
  "2_initiation_stage": [
    "niw-eb1-어플리케이션",
    "sme-transformation",
    "3월-아티클리딩-및-리뷰",
    "pp_2026_01_media_ip",
    "hrd-weird-bias",
    "rp_2026_03_ai_critical_thinking_with_drpark"
  ],
  "3_in_development": [
    "student-performance",
    "rp_2026_05_1_instutional_thriving_conceptual_paper",
    "gabqca",
    "pm-master-online"
  ],
  "5_completed": [
    "ai-work-chagne",
    "pm-master-local",
    "packagelist",
    "localingo",
    "LLMDash_latest",
    "chad-app-template-light",
    "chad-app-template"
  ],
  "4_in_testing": [
    "rp_quick_microfinance_manuscript",
    "rp_2024_02_women-leadership",
    "rp_2025_04_communication_rem_cloudbro"
  ],
  "6_archived": [
    "claudbro-national-applicaiton",
    "rp_2024_01_tourism",
    "LLMDash_latest",
    "localingo",
    "packagelist",
    "chad-app-template",
    "chad-app-template-light"
  ]
}